{
  "project_info": {
    "project_number": "907376839187",
    "project_id": "moviedbteam1",
    "storage_bucket": "moviedbteam1.appspot.com"
  },
  "client": [
    {
      "client_info": {
        "mobilesdk_app_id": "1:907376839187:android:953774e4b3021e84640de6",
        "android_client_info": {
          "package_name": "com.moviedbapp"
        }
      },
      "oauth_client": [
        {
          "client_id": "907376839187-n5km8otonobmlbk82c1o53iobrsbjh22.apps.googleusercontent.com",
          "client_type": 3
        }
      ],
      "api_key": [
        {
          "current_key": "AIzaSyDerY7kt-9bGLZPf_IK9P0JNe-U94gQEug"
        }
      ],
      "services": {
        "appinvite_service": {
          "other_platform_oauth_client": [
            {
              "client_id": "907376839187-n5km8otonobmlbk82c1o53iobrsbjh22.apps.googleusercontent.com",
              "client_type": 3
            }
          ]
        }
      }
    }
  ],
  "configuration_version": "1"
}